wise/__init__.py
wise/bugfinder.py
wise/cli.py
wise/helpers.py
wise/imp.py
wise/parser.py
wise/streams.py
wise/symex.py
wise/imp_language/ImpLanguageLexer.py
wise/imp_language/ImpLanguageListener.py
wise/imp_language/ImpLanguageParser.py
wise/imp_language/__init__.py
wise_se-0.0.7.dist-info/COPYING
wise_se-0.0.7.dist-info/METADATA
wise_se-0.0.7.dist-info/WHEEL
wise_se-0.0.7.dist-info/entry_points.txt
wise_se-0.0.7.dist-info/top_level.txt
wise_se-0.0.7.dist-info/RECORD
