Metadata-Version: 2.1
Name: wise-se
Version: 0.0.7
Summary: A Python re-implementation of the proven-correct symbolic executor WiSE
Home-page: https://github.com/acorrenson/WiSE
Author: Arthur Correnson and Dominic Steinhoefel
Author-email: Arthur Correnson <arthur.correnson@ens-rennes.fr>, Dominic Steinhoefel <dominic.steinhoefel@cispa.de>
License: GNU GENERAL PUBLIC LICENSE
Project-URL: Homepage, https://github.com/acorrenson/WiSE
Project-URL: Bug Tracker, https://github.com/acorrenson/WiSE/issues/
Classifier: Intended Audience :: Science/Research
Classifier: License :: OSI Approved :: GNU General Public License v3 (GPLv3)
Classifier: Programming Language :: Python :: 3.10
Classifier: Operating System :: OS Independent
Classifier: Topic :: Scientific/Engineering
Classifier: Topic :: Software Development :: Testing
Requires-Python: >=3.10
License-File: COPYING
Requires-Dist: antlr4-python3-runtime ==4.11
Requires-Dist: packaging >=21.3
Requires-Dist: toolz >=0.12.0
Requires-Dist: wheel >=0.37.1
Requires-Dist: z3-solver >=4.8.17.0
Provides-Extra: dev
Requires-Dist: black >=22.8.0 ; extra == 'dev'
Requires-Dist: build >=0.8.0 ; extra == 'dev'
Requires-Dist: twine >=4.0.1 ; extra == 'dev'
Provides-Extra: test
Requires-Dist: pytest-pycharm >=0.7.0 ; extra == 'test'
Requires-Dist: pytest-xdist >=2.4.0 ; extra == 'test'
Requires-Dist: pytest >=7.1.2 ; extra == 'test'
